workcraft/__init__.py
workcraft/__main__.py
workcraft/constants.py
workcraft/core.py
workcraft/db.py
workcraft/models.py
workcraft/peon.py
workcraft/settings.py
workcraft/utils.py
workcraft/sqls/a_create_logs_table.sql
workcraft/sqls/b_create_peons_table.sql
workcraft/sqls/c_create_bountyboard_tables.sql
workcraft/sqls/d_reopen_failed_tasks_procedure.sql
workcraft/sqls/e_self_correct_task_procedure.sql
workcraft/sqls/f_self_correcting_task_event.sql
workcraft/sqls/g_reopen_failed_tasks_event.sql
workcraft/sqls/h_check_dead_workers_procedure.sql
workcraft/sqls/i_check_dead_worker_event.sql
workcraft/sqls/j_create_last_updated_index.sql
workcraft/sqls/k_create_dequeue_index.sql
workcraft-0.5.27.dist-info/METADATA
workcraft-0.5.27.dist-info/WHEEL
workcraft-0.5.27.dist-info/RECORD
