Metadata-Version: 2.3
Name: workcraft
Version: 0.5.27
Summary: A simple, lightweight, database-only, worker library in Python
Requires-Python: >=3.10
Requires-Dist: aiomysql>=0.2.0
Requires-Dist: asyncio>=3.4.3
Requires-Dist: beartype>=0.19.0
Requires-Dist: cryptography>=43.0.1
Requires-Dist: fire>=0.7.0
Requires-Dist: loguru>=0.7.2
Requires-Dist: nox>=2024.4.15
Requires-Dist: pre-commit>=4.0.0
Requires-Dist: pydantic>=2.9.2
Requires-Dist: pymysql>=1.1.1
Requires-Dist: python-dotenv>=1.0.1
Requires-Dist: sqlalchemy>=2.0.35
Provides-Extra: dev
Requires-Dist: mkdocs; extra == 'dev'
Requires-Dist: pre-commit; extra == 'dev'
Requires-Dist: pytest; extra == 'dev'
